[
  {
    "id": 1,
    "author": "Nguyễn Thành Nam",
    "date": "25, Nov 2025",
    "rating": 5,
    "title": "Trải Nghiệm Tuyệt Vời",
    "content": "Rất hài lòng với dịch vụ này. Nhân viên rất nhiệt tình, không gian sạch sẽ và thoải mái. Sẽ quay lại lần sau để trải nghiệm thêm nhiều dịch vụ khác của các bạn nữa nhé. Cảm ơn các bạn rất nhiều.",
    "image": "https://feji.us/wz42t0"
  },
  {
    "id": 2,
    "author": "Trần Thị Hạnh",
    "date": "20, Nov 2025",
    "rating": 4,
    "title": "Dịch Vụ Tốt",
    "content": "Dịch vụ tốt, nhân viên thân thiện và chuyên nghiệp. Tuy nhiên, có thể cải thiện một số điểm nhỏ để tốt hơn. Sẽ quay lại trong tương lai gần và giới thiệu cho bạn bè.",
    "image": "https://feji.us/wz42t0"
  },
  {
    "id": 3,
    "author": "Lê Văn Khải",
    "date": "15, Nov 2025",
    "rating": 5,
    "title": "Tuyệt Vời",
    "content": "Dịch vụ tuyệt vời. Mọi thứ đều hoàn hảo từ chất lượng đến phục vụ. Nhân viên thân thiện, nhiệt tình và luôn sẵn sàng hỗ trợ khách hàng. Rất đáng giá tiền.",
    "image": "https://feji.us/wz42t0"
  },
  {
    "id": 4,
    "author": "Phạm Thị Huyền",
    "date": "10, Nov 2025",
    "rating": 3,
    "title": "Tạm Được",
    "content": "Tạm được, không có gì đặc biệt. Dịch vụ ổn nhưng có thể cải thiện hơn để thu hút khách hàng hơn. Nhân viên cần chuyên nghiệp và nhiệt tình hơn. Cảm ơn.",
    "image": "https://feji.us/wz42t0"
  },
  {
    "id": 5,
    "author": "Vũ Văn Long",
    "date": "5, Nov 2025",
    "rating": 4,
    "title": "Hài Lòng",
    "content": "Hài lòng với dịch vụ. Nhân viên thân thiện, phục vụ tốt và chuyên nghiệp. Không gian sạch sẽ, thoải mái. Sẽ quay lại và giới thiệu cho bạn bè và người thân.",
    "image": "https://feji.us/wz42t0"
  },
  {
    "id": 6,
    "author": "Nguyễn Văn Minh",
    "date": "1, Nov 2025",
    "rating": 5,
    "title": "Trải Nghiệm Đáng Nhớ",
    "content": "Dịch vụ rất tốt. Nhân viên nhiệt tình và chuyên nghiệp. Sẽ quay lại và trải nghiệm thêm nhiều dịch vụ khác. Rất đáng giá tiền. Cảm ơn các bạn đã phục vụ tận tình.",
    "image": "https://feji.us/wz42t0"
  },
  {
    "id": 7,
    "author": "Trần Thị Lan",
    "date": "28, Oct 2025",
    "rating": 4,
    "title": "Dịch Vụ Tốt",
    "content": "Rất tốt, sẽ giới thiệu bạn bè. Dịch vụ chuyên nghiệp và chất lượng. Nhân viên thân thiện, luôn sẵn sàng hỗ trợ khách hàng. Không gian sạch sẽ, thoải mái. Sẽ quay lại.",
    "image": "https://feji.us/wz42t0"
  },
  {
    "id": 8,
    "author": "Lê Văn Hùng",
    "date": "25, Oct 2025",
    "rating": 5,
    "title": "Rất Tốt",
    "content": "Dịch vụ rất tốt. Không gian sạch sẽ, nhân viên thân thiện và chuyên nghiệp. Sẽ quay lại lần sau để trải nghiệm thêm nhiều dịch vụ khác nữa. Cảm ơn các bạn.",
    "image": "https://feji.us/wz42t0"
  },
  {
    "id": 9,
    "author": "Phạm Thị Mai",
    "date": "20, Oct 2025",
    "rating": 4,
    "title": "Hài Lòng",
    "content": "Hài lòng với trải nghiệm. Nhân viên nhiệt tình và chuyên nghiệp. Không gian sạch sẽ, thoải mái. Sẽ quay lại lần sau để trải nghiệm thêm nhiều dịch vụ khác.",
    "image": "https://feji.us/wz42t0"
  },
  {
    "id": 10,
    "author": "Vũ Văn Quang",
    "date": "15, Oct 2025",
    "rating": 2,
    "title": "Không Hài Lòng",
    "content": "Dịch vụ tệ, không quay lại. Nhân viên thiếu chuyên nghiệp, không thân thiện. Không gian không sạch sẽ. Cần cải thiện nhiều để thu hút khách hàng.",
    "image": "https://feji.us/wz42t0"
  },
  {
    "id": 11,
    "author": "Nguyễn Văn Hùng",
    "date": "10, Oct 2025",
    "rating": 5,
    "title": "Tuyệt Vời",
    "content": "Rất hài lòng với dịch vụ. Nhân viên thân thiện và nhiệt tình. Không gian sạch sẽ, thoải mái. Sẽ quay lại lần sau để trải nghiệm thêm nhiều dịch vụ khác nữa.",
    "image": "https://feji.us/wz42t0"
  },
  {
    "id": 12,
    "author": "Trần Thị Thu",
    "date": "5, Oct 2025",
    "rating": 4,
    "title": "Dịch Vụ Chất Lượng",
    "content": "Dịch vụ tốt, đáng giá tiền. Nhân viên nhiệt tình và chuyên nghiệp. Không gian sạch sẽ, thoải mái. Sẽ quay lại lần sau để trải nghiệm thêm nhiều dịch vụ khác nữa.",
    "image": "https://feji.us/wz42t0"
  },
  {
    "id": 13,
    "author": "Lê Văn Phú",
    "date": "1, Oct 2025",
    "rating": 5,
    "title": "Trải Nghiệm Tuyệt Vời",
    "content": "Dịch vụ tuyệt vời, sẽ quay lại. Nhân viên chuyên nghiệp và nhiệt tình. Không gian sạch sẽ, thoải mái. Sẽ quay lại lần sau để trải nghiệm thêm nhiều dịch vụ khác.",
    "image": "https://feji.us/wz42t0"
  },
  {
    "id": 14,
    "author": "Phạm Thị Thảo",
    "date": "28, Sep 2025",
    "rating": 4,
    "title": "Dịch Vụ Tốt",
    "content": "Hài lòng với dịch vụ. Nhân viên thân thiện và nhiệt tình. Không gian sạch sẽ, thoải mái. Sẽ quay lại lần sau để trải nghiệm thêm nhiều dịch vụ khác.",
    "image": "https://feji.us/wz42t0"
  },
  {
    "id": 15,
    "author": "Vũ Văn Đạt",
    "date": "25, Sep 2025",
    "rating": 5,
    "title": "Tuyệt Vời",
    "content": "Dịch vụ rất tốt, đáng tiền. Nhân viên thân thiện và nhiệt tình. Không gian sạch sẽ, thoải mái. Sẽ quay lại lần sau để trải nghiệm thêm nhiều dịch vụ khác.",
    "image": "https://feji.us/wz42t0"
  },
  {
    "id": 16,
    "author": "Nguyễn Văn Tài",
    "date": "20, Sep 2025",
    "rating": 3,
    "title": "Tạm Được",
    "content": "Dịch vụ ổn, không quá đặc biệt. Nhân viên cần cải thiện để chuyên nghiệp hơn. Không gian sạch sẽ nhưng cần đầu tư thêm. Cảm ơn các bạn.",
    "image": "https://feji.us/wz42t0"
  },
  {
    "id": 17,
    "author": "Trần Thị Ngọc",
    "date": "15, Sep 2025",
    "rating": 4,
    "title": "Hài Lòng",
    "content": "Dịch vụ tốt, sẽ quay lại. Nhân viên nhiệt tình và chuyên nghiệp. Không gian sạch sẽ, thoải mái. Sẽ quay lại lần sau để trải nghiệm thêm nhiều dịch vụ khác.",
    "image": "https://feji.us/wz42t0"
  },
  {
    "id": 18,
    "author": "Lê Văn Bình",
    "date": "10, Sep 2025",
    "rating": 5,
    "title": "Trải Nghiệm Đáng Nhớ",
    "content": "Dịch vụ tuyệt vời, đáng giá tiền. Nhân viên chuyên nghiệp và nhiệt tình. Không gian sạch sẽ, thoải mái. Sẽ quay lại lần sau để trải nghiệm thêm nhiều dịch vụ.",
    "image": "https://feji.us/wz42t0"
  },
  {
    "id": 19,
    "author": "Phạm Thị Thanh",
    "date": "5, Sep 2025",
    "rating": 4,
    "title": "Dịch Vụ Tốt",
    "content": "Hài lòng với dịch vụ. Nhân viên thân thiện và nhiệt tình. Không gian sạch sẽ, thoải mái. Sẽ quay lại lần sau để trải nghiệm thêm nhiều dịch vụ khác.",
    "image": "https://feji.us/wz42t0"
  },
  {
    "id": 20,
    "author": "Vũ Văn Khoa",
    "date": "1, Sep 2025",
    "rating": 5,
    "title": "Rất Tốt",
    "content": "Dịch vụ rất tốt, sẽ quay lại. Nhân viên nhiệt tình và chuyên nghiệp. Không gian sạch sẽ, thoải mái. Sẽ quay lại lần sau để trải nghiệm thêm nhiều dịch vụ khác.",
    "image": "https://feji.us/wz42t0"
  },
  {
    "id": 21,
    "author": "Nguyễn Văn Quý",
    "date": "28, Aug 2025",
    "rating": 4,
    "title": "Hài Lòng",
    "content": "Dịch vụ tốt, đáng tiền. Nhân viên nhiệt tình và chuyên nghiệp. Không gian sạch sẽ, thoải mái. Sẽ quay lại lần sau để trải nghiệm thêm nhiều dịch vụ khác.",
    "image": "https://feji.us/wz42t0"
  },
  {
    "id": 22,
    "author": "Trần Thị Nguyệt",
    "date": "25, Aug 2025",
    "rating": 2,
    "title": "Rất Tệ",
    "content": "Dịch vụ rất tệ, không quay lại. Nhân viên không thân thiện và thiếu chuyên nghiệp. Không gian không sạch sẽ. Cần cải thiện nhiều để thu hút khách hàng hơn.",
    "image": "https://feji.us/wz42t0"
  }
]
